fiduswriter/.mathlive_bundle_cache.json
fiduswriter/.schema_export_cache.json
fiduswriter/asgi.py
fiduswriter/configuration-default.py
fiduswriter/dev-requirements.txt
fiduswriter/fiduswriter.spec
fiduswriter/manage.py
fiduswriter/mysql-requirements.txt
fiduswriter/postgresql-requirements.txt
fiduswriter/requirements.txt
fiduswriter/test-requirements.txt
fiduswriter/version.txt
fiduswriter/base/__init__.py
fiduswriter/base/admin.py
fiduswriter/base/apps.py
fiduswriter/base/base_consumer.py
fiduswriter/base/consumers.py
fiduswriter/base/decorators.py
fiduswriter/base/html_email.py
fiduswriter/base/models.py
fiduswriter/base/package.json5
fiduswriter/base/root_urls.py
fiduswriter/base/routing.py
fiduswriter/base/rspack.config.template.js
fiduswriter/base/settings.py
fiduswriter/base/urls.py
fiduswriter/base/views.py
fiduswriter/base/ws_urls.py
fiduswriter/base/fixtures/initial_terms.json
fiduswriter/base/helpers/__init__.py
fiduswriter/base/helpers/ws.py
fiduswriter/base/management/__init__.py
fiduswriter/base/management/commands/__init__.py
fiduswriter/base/management/commands/bundle_mathlive.py
fiduswriter/base/management/commands/collectstatic.py
fiduswriter/base/management/commands/compilemessages.py
fiduswriter/base/management/commands/initadmin.py
fiduswriter/base/management/commands/runserver.py
fiduswriter/base/management/commands/setup.py
fiduswriter/base/management/commands/startproject.py
fiduswriter/base/migrations/0001_initial.py
fiduswriter/base/migrations/__init__.py
fiduswriter/base/setup_page/index.html
fiduswriter/base/static/css/add_remove_dialog.css
fiduswriter/base/static/css/admin.css
fiduswriter/base/static/css/alerts.css
fiduswriter/base/static/css/buttons.css
fiduswriter/base/static/css/colors.css
fiduswriter/base/static/css/common.css
fiduswriter/base/static/css/content_menu.css
fiduswriter/base/static/css/data_table.css
fiduswriter/base/static/css/dialog.css
fiduswriter/base/static/css/dialog_table.css
fiduswriter-4.0.17.dist-info/licenses/AUTHORS
fiduswriter-4.0.17.dist-info/licenses/LICENSE
fiduswriter-4.0.17.dist-info/METADATA
fiduswriter-4.0.17.dist-info/WHEEL
fiduswriter-4.0.17.dist-info/entry_points.txt
fiduswriter-4.0.17.dist-info/top_level.txt
fiduswriter-4.0.17.dist-info/RECORD
